landregistry/security_headers/__init__.py
landregistry/security_headers/csp_reporting.py
landregistry/security_headers/exceptions.py
landregistry/security_headers/header_defaults.py
landregistry/security_headers/py.typed
landregistry/security_headers/response_without_csp.py
landregistry/security_headers/security_headers.py
landregistry_security_headers-1.0.5.dist-info/METADATA
landregistry_security_headers-1.0.5.dist-info/WHEEL
landregistry_security_headers-1.0.5.dist-info/top_level.txt
landregistry_security_headers-1.0.5.dist-info/RECORD
