Metadata-Version: 2.1
Name: landregistry-security-headers
Version: 1.0.5
Summary: Standardised exception security related HTTP headers for HMLR Flask applications
Author: Ian Harvey
Author-email: ian.harvey@landregistry.gov.uk
License: MIT
Requires-Python: >=3.9
Requires-Dist: flask >=2.2.0
